maybell_quantum/__init__.py
maybell_quantum/fridgedb.py
maybell_quantum/helpers.py
maybell_quantum/mock_data_generator.py
maybell_quantum/models.py
maybell_quantum/mongo_time_series.py
maybell_quantum-1.1.0.dist-info/LICENSE
maybell_quantum-1.1.0.dist-info/METADATA
maybell_quantum-1.1.0.dist-info/WHEEL
maybell_quantum-1.1.0.dist-info/top_level.txt
maybell_quantum-1.1.0.dist-info/RECORD
