Metadata-Version: 2.2
Name: maybell_quantum
Version: 1.1.0
Summary: API for pulling data from Maybell Quantum dilution refrigerators.
Author-email: Alex Olivas <alex@maybellquantum.com>
Maintainer-email: Josh Moler <josh@maybellquantum.com>, Conor Parlo Simon <conor@maybellquantum.com>, Ben Waters <benwaters@maybellquantum.com>
Project-URL: Homepage, https://github.com/MaybellQuantum/maybell_quantum
Classifier: Programming Language :: Python :: 3
Classifier: License :: OSI Approved :: Apache Software License
Classifier: Operating System :: OS Independent
Requires-Python: >=3.10
License-File: LICENSE
Requires-Dist: influxdb-client
Requires-Dist: pymongo
Requires-Dist: matplotlib
Requires-Dist: pandas
